{
  "id": "retrospective-53-minutes",
  "tracks": [
    { "track": 1, "audio": "assets/audio/retrospective-53-minutes/01.mp3" },
    { "track": 2, "audio": "assets/audio/retrospective-53-minutes/02.mp3" },
    { "track": 3, "audio": "assets/audio/retrospective-53-minutes/03.mp3" },
    { "track": 4, "audio": "assets/audio/retrospective-53-minutes/04.mp3" },
    { "track": 5, "audio": "assets/audio/retrospective-53-minutes/05.mp3" },
    { "track": 6, "audio": "assets/audio/retrospective-53-minutes/06.mp3" },
    { "track": 7, "audio": "assets/audio/retrospective-53-minutes/07.mp3" },
    { "track": 8, "audio": "assets/audio/retrospective-53-minutes/08.mp3" },
    { "track": 9, "audio": "assets/audio/retrospective-53-minutes/09.mp3" },
    { "track": 10, "audio": "assets/audio/retrospective-53-minutes/10.mp3" },
    { "track": 11, "audio": "assets/audio/retrospective-53-minutes/11.mp3" }
  ],
  "story": [
    { "track": 1, "title": { "zh": "ヒロシゲ36号 ～ Neo Super-Express", "ja": "ヒロシゲ36号 ～ Neo Super-Express" }, "text": { "zh": "", "ja": "" } },
    { "track": 2, "title": { "zh": "53ミニッツの青い海", "ja": "53ミニッツの青い海" }, "text": { "zh": "", "ja": "" } },
    { "track": 3, "title": { "zh": "竹取飛翔 ～ Lunatic Princess", "ja": "竹取飛翔 ～ Lunatic Princess" }, "text": { "zh": "", "ja": "" } },
    { "track": 4, "title": { "zh": "彼岸帰航 ～ Riverside View", "ja": "彼岸帰航 ～ Riverside View" }, "text": { "zh": "", "ja": "" } },
    { "track": 5, "title": { "zh": "青木ヶ原の伝説", "ja": "青木ヶ原の伝説" }, "text": { "zh": "", "ja": "" } },
    { "track": 6, "title": { "zh": "お宇佐さまの素い幡", "ja": "お宇佐さまの素い幡" }, "text": { "zh": "", "ja": "" } },
    { "track": 7, "title": { "zh": "月まで届け、不死の煙", "ja": "月まで届け、不死の煙" }, "text": { "zh": "", "ja": "" } },
    { "track": 8, "title": { "zh": "レトロスペクティブ京都", "ja": "レトロスペクティブ京都" }, "text": { "zh": "", "ja": "" } },
    { "track": 9, "title": { "zh": "ラクトガール ～ 少女密室", "ja": "ラクトガール ～ 少女密室" }, "text": { "zh": "", "ja": "" } },
    { "track": 10, "title": { "zh": "千年幻想郷 ～ History of the Moon", "ja": "千年幻想郷 ～ History of the Moon" }, "text": { "zh": "", "ja": "" } },
    { "track": 11, "title": { "zh": "最も澄みわたる空と海", "ja": "最も澄みわたる空と海" }, "text": { "zh": "", "ja": "" } }
  ]
}
